odoo/addons/sale_order_sale_partner/LICENSE
odoo/addons/sale_order_sale_partner/README.rst
odoo/addons/sale_order_sale_partner/__init__.py
odoo/addons/sale_order_sale_partner/__manifest__.py
odoo/addons/sale_order_sale_partner/i18n/de.po
odoo/addons/sale_order_sale_partner/images/screen.png
odoo/addons/sale_order_sale_partner/models/__init__.py
odoo/addons/sale_order_sale_partner/models/sale_order.py
odoo/addons/sale_order_sale_partner/static/description/icon.png
odoo/addons/sale_order_sale_partner/static/description/index.html
odoo/addons/sale_order_sale_partner/tests/TEST_INSTRUCTIONS.rst
odoo/addons/sale_order_sale_partner/views/sale_order.xml
odoo_addon_sale_order_sale_partner-16.0.1.0.0.dist-info/METADATA
odoo_addon_sale_order_sale_partner-16.0.1.0.0.dist-info/WHEEL
odoo_addon_sale_order_sale_partner-16.0.1.0.0.dist-info/top_level.txt
odoo_addon_sale_order_sale_partner-16.0.1.0.0.dist-info/RECORD
